resourcetools/__init__.py
resourcetools/getters.py
resourcetools/py.typed
resourcetools/state.py
resourcetools-1.0.0.dist-info/METADATA
resourcetools-1.0.0.dist-info/WHEEL
resourcetools-1.0.0.dist-info/licenses/LICENSE
resourcetools-1.0.0.dist-info/RECORD
