Metadata-Version: 2.4
Name: resourcetools
Version: 1.0.0
Summary: A lightweight Python package for managing application resources (icons, images, translations, etc.) in a clean, importlib-compatible way — ideal for PySide6 and other GUI or CLI apps.
Author-email: Rafal Padkowski <rafaelp@poczta.onet.pl>
License-Expression: MIT
License-File: LICENSE
Requires-Python: >=3.9
